README.rst
setup.py
qingfeng/__init__.py
qingfeng/heytest.py
qingfeng.egg-info/PKG-INFO
qingfeng.egg-info/SOURCES.txt
qingfeng.egg-info/dependency_links.txt
qingfeng.egg-info/requires.txt
qingfeng.egg-info/top_level.txt